{
  "ibk": [
    {
      "id": "IjzjndubTdg",
      "titulo": "Culto Doutrinário | 17.05",
      "data": "2026-05-18",
      "thumbnail": "https://i.ytimg.com/vi/IjzjndubTdg/maxresdefault.jpg"
    },
    {
      "id": "TME-m8yjBsY",
      "titulo": "Culto da Família | 17.05",
      "data": "2026-05-17",
      "thumbnail": "https://i.ytimg.com/vi/TME-m8yjBsY/maxresdefault.jpg"
    },
    {
      "id": "fYtc-hhWjPM",
      "titulo": "Traição, perdão e uma família restaurada por Deus | IBKAST EP 05",
      "data": "2026-05-15",
      "thumbnail": "https://i.ytimg.com/vi/fYtc-hhWjPM/maxresdefault.jpg"
    },
    {
      "id": "DInfA4mrjac",
      "titulo": "Conferência da Família | 13.05",
      "data": "2026-05-14",
      "thumbnail": "https://i.ytimg.com/vi/DInfA4mrjac/maxresdefault.jpg"
    },
    {
      "id": "zRRT0fZ7HUc",
      "titulo": "Culto Doutrinário | 10.05",
      "data": "2026-05-11",
      "thumbnail": "https://i.ytimg.com/vi/zRRT0fZ7HUc/maxresdefault.jpg"
    }
  ],
  "pedro": [
    {
      "id": "aEVYkitZ544",
      "titulo": "Ai de quem escandaliza Lc 17.1,2",
      "data": "2026-05-18",
      "thumbnail": "https://i.ytimg.com/vi/aEVYkitZ544/maxresdefault.jpg"
    },
    {
      "id": "gY-98-Eiuuc",
      "titulo": "Será que estou certo? Mt 7.5",
      "data": "2026-05-15",
      "thumbnail": "https://i.ytimg.com/vi/gY-98-Eiuuc/maxresdefault.jpg"
    },
    {
      "id": "y2OnTikPDCQ",
      "titulo": "Filho celebrado Lc 15.22-24",
      "data": "2026-05-14",
      "thumbnail": "https://i.ytimg.com/vi/y2OnTikPDCQ/maxresdefault.jpg"
    },
    {
      "id": "m8_Fk2Ej8g8",
      "titulo": "Filho abraçado Lc 15.20",
      "data": "2026-05-13",
      "thumbnail": "https://i.ytimg.com/vi/m8_Fk2Ej8g8/maxresdefault.jpg"
    },
    {
      "id": "XFRCl7AXKxE",
      "titulo": "Filho Convertidos Lc 15.17-19",
      "data": "2026-05-12",
      "thumbnail": "https://i.ytimg.com/vi/XFRCl7AXKxE/maxresdefault.jpg"
    }
  ],
  "podcasts": [
    {
      "id": "fYtc-hhWjPM",
      "titulo": "Traição, perdão e uma família restaurada por Deus | IBKAST EP 05",
      "data": "2026-05-15",
      "thumbnail": "https://i.ytimg.com/vi/fYtc-hhWjPM/maxresdefault.jpg"
    },
    {
      "id": "VOOwK7csjxM",
      "titulo": "O que fazer quando Deus está em silêncio | IBKAST EP 04",
      "data": "2026-04-10",
      "thumbnail": "https://i.ytimg.com/vi/VOOwK7csjxM/maxresdefault.jpg"
    },
    {
      "id": "r2WwnnNH6R8",
      "titulo": "Deus escolheu agir através de pessoas imperfeitas",
      "data": "2026-03-30",
      "thumbnail": "https://i.ytimg.com/vi/r2WwnnNH6R8/maxresdefault.jpg"
    },
    {
      "id": "1UL5yAy8_2U",
      "titulo": "A verdade sobre propósito que ninguém te contou | IBKAST EP 03",
      "data": "2026-03-19",
      "thumbnail": "https://i.ytimg.com/vi/1UL5yAy8_2U/maxresdefault.jpg"
    },
    {
      "id": "3_DNtAuFWHQ",
      "titulo": "Casamento, igreja e chamado pastoral | IBKAST EP 02",
      "data": "2026-03-13",
      "thumbnail": "https://i.ytimg.com/vi/3_DNtAuFWHQ/maxresdefault.jpg"
    }
  ],
  "updatedAt": "2026-05-18T23:28:04.702Z"
}